{
  "version": "7",
  "dialect": "postgresql",
  "entries": [
    {
      "idx": 0,
      "version": "7",
      "when": 1749469426319,
      "tag": "0000_wakeful_piledriver",
      "breakpoints": true
    },
    {
      "idx": 1,
      "version": "7",
      "when": 1750773597828,
      "tag": "0001_condemned_ender_wiggin",
      "breakpoints": true
    },
    {
      "idx": 2,
      "version": "7",
      "when": 1754003181625,
      "tag": "0002_organic_killer_shrike",
      "breakpoints": true
    },
    {
      "idx": 3,
      "version": "7",
      "when": 1756563983181,
      "tag": "0003_worried_jack_power",
      "breakpoints": true
    },
    {
      "idx": 4,
      "version": "7",
      "when": 1756838065703,
      "tag": "0004_sloppy_chamber",
      "breakpoints": true
    }
  ]
}